SocialED/__init__.py
SocialED/version.py
SocialED/dataset/__init__.py
SocialED/dataset/dataloader.py
SocialED/detector/__init__.py
SocialED/detector/adpsemevent.py
SocialED/detector/bert.py
SocialED/detector/bilstm.py
SocialED/detector/clkd.py
SocialED/detector/etgnn.py
SocialED/detector/eventx.py
SocialED/detector/finevent.py
SocialED/detector/glove.py
SocialED/detector/hcrc.py
SocialED/detector/hisevent.py
SocialED/detector/hypersed.py
SocialED/detector/kpgnn.py
SocialED/detector/lda.py
SocialED/detector/qsgnn.py
SocialED/detector/rplmsed.py
SocialED/detector/sbert.py
SocialED/detector/uclsed.py
SocialED/detector/wmd.py
SocialED/detector/word2vec.py
SocialED/metrics/__init__.py
SocialED/metrics/metric.py
SocialED/model/__init__.py
SocialED/tests/__init__.py
SocialED/tests/test_adpsemevent.py
SocialED/tests/test_bert.py
SocialED/tests/test_bilstm.py
SocialED/tests/test_clkd.py
SocialED/tests/test_data_process.py
SocialED/tests/test_dataloader.py
SocialED/tests/test_eventx.py
SocialED/tests/test_finevent.py
SocialED/tests/test_glove.py
SocialED/tests/test_hcrc.py
SocialED/tests/test_hisevent.py
SocialED/tests/test_hypersed.py
SocialED/tests/test_kpgnn.py
SocialED/tests/test_lda.py
SocialED/tests/test_metric.py
SocialED/tests/test_qsgnn.py
SocialED/tests/test_rplmsed.py
SocialED/tests/test_sbert.py
SocialED/tests/test_uclsed.py
SocialED/tests/test_utility.py
SocialED/tests/test_wmd.py
SocialED/tests/test_word2vec.py
SocialED/utils/__init__.py
SocialED/utils/dataprocess.py
SocialED/utils/utility.py
SocialED-1.1.7.dist-info/LICENSE
SocialED-1.1.7.dist-info/METADATA
SocialED-1.1.7.dist-info/WHEEL
SocialED-1.1.7.dist-info/top_level.txt
SocialED-1.1.7.dist-info/RECORD
