Metadata-Version: 2.1
Name: SocialED
Version: 1.1.7
Summary: A Python Library for Social Event Detection
Home-page: https://github.com/RingBDStack/SocialED
Author: beici
Author-email: zhangkun23@buaa.edu.cn
Classifier: Programming Language :: Python :: 3.8
Classifier: License :: OSI Approved :: MIT License
Classifier: Operating System :: OS Independent
Requires-Python: >=3.8
License-File: LICENSE
Requires-Dist: accelerate ==0.28.0
Requires-Dist: aiohttp ==3.9.5
Requires-Dist: aiosignal ==1.3.1
Requires-Dist: alabaster ==0.7.13
Requires-Dist: annotated-types ==0.6.0
Requires-Dist: anyio ==4.3.0
Requires-Dist: async-timeout ==4.0.3
Requires-Dist: attrs ==23.2.0
Requires-Dist: Babel ==2.15.0
Requires-Dist: backports.tarfile ==1.2.0
Requires-Dist: beautifulsoup4 ==4.12.3
Requires-Dist: bitsandbytes ==0.42.0
Requires-Dist: blis ==0.7.11
Requires-Dist: catalogue ==2.0.10
Requires-Dist: certifi ==2024.2.2
Requires-Dist: cffi ==1.17.0
Requires-Dist: charset-normalizer ==3.3.2
Requires-Dist: click ==8.1.7
Requires-Dist: cloudpathlib ==0.16.0
Requires-Dist: cmake ==3.28.4
Requires-Dist: commonmark ==0.9.1
Requires-Dist: confection ==0.1.4
Requires-Dist: contourpy ==1.1.1
Requires-Dist: coverage ==7.6.1
Requires-Dist: coveralls ==4.0.1
Requires-Dist: cryptography ==43.0.0
Requires-Dist: cycler ==0.12.1
Requires-Dist: cymem ==2.0.8
Requires-Dist: Cython ==0.29.37
Requires-Dist: datasets ==3.0.1
Requires-Dist: decorator ==5.1.1
Requires-Dist: dgl ==0.6.0
Requires-Dist: dgl-cu110 ==0.6.1
Requires-Dist: dill ==0.3.8
Requires-Dist: docopt ==0.6.2
Requires-Dist: docutils ==0.20.1
Requires-Dist: exceptiongroup ==1.2.0
Requires-Dist: faiss-gpu ==1.7.2
Requires-Dist: fastapi ==0.110.0
Requires-Dist: filelock ==3.16.1
Requires-Dist: fonttools ==4.53.1
Requires-Dist: frozenlist ==1.4.1
Requires-Dist: fsspec ==2024.3.1
Requires-Dist: furo ==2024.8.6
Requires-Dist: gensim ==4.3.2
Requires-Dist: geoopt ==0.5.0
Requires-Dist: gitdb ==4.0.11
Requires-Dist: GitPython ==3.1.43
Requires-Dist: h11 ==0.14.0
Requires-Dist: hdbscan ==0.8.36
Requires-Dist: huggingface-hub ==0.25.1
Requires-Dist: idna ==3.7
Requires-Dist: ignite ==1.1.0
Requires-Dist: imagesize ==1.4.1
Requires-Dist: importlib-metadata ==8.2.0
Requires-Dist: importlib-resources ==6.4.0
Requires-Dist: iniconfig ==2.0.0
Requires-Dist: jaraco.classes ==3.4.0
Requires-Dist: jaraco.context ==5.3.0
Requires-Dist: jaraco.functools ==4.0.2
Requires-Dist: jeepney ==0.8.0
Requires-Dist: Jinja2 ==3.1.3
Requires-Dist: joblib ==1.4.2
Requires-Dist: keyring ==25.3.0
Requires-Dist: kiwisolver ==1.4.5
Requires-Dist: langcodes ==3.4.0
Requires-Dist: language-data ==1.2.0
Requires-Dist: latexcodec ==3.0.0
Requires-Dist: lit ==18.1.2
Requires-Dist: marisa-trie ==1.1.1
Requires-Dist: markdown-it-py ==3.0.0
Requires-Dist: MarkupSafe ==2.1.5
Requires-Dist: matplotlib ==3.7.5
Requires-Dist: mdurl ==0.1.2
Requires-Dist: more-itertools ==10.4.0
Requires-Dist: mpmath ==1.3.0
Requires-Dist: multidict ==6.0.5
Requires-Dist: multiprocess ==0.70.16
Requires-Dist: munkres ==1.1.4
Requires-Dist: murmurhash ==1.0.10
Requires-Dist: networkx ==3.1
Requires-Dist: nh3 ==0.2.18
Requires-Dist: numpy ==1.24.4
Requires-Dist: nvidia-cublas-cu11 ==11.10.3.66
Requires-Dist: nvidia-cublas-cu12 ==12.1.3.1
Requires-Dist: nvidia-cuda-cupti-cu11 ==11.7.101
Requires-Dist: nvidia-cuda-cupti-cu12 ==12.1.105
Requires-Dist: nvidia-cuda-nvrtc-cu11 ==11.7.99
Requires-Dist: nvidia-cuda-nvrtc-cu12 ==12.1.105
Requires-Dist: nvidia-cuda-runtime-cu11 ==11.7.99
Requires-Dist: nvidia-cuda-runtime-cu12 ==12.1.105
Requires-Dist: nvidia-cudnn-cu11 ==8.5.0.96
Requires-Dist: nvidia-cudnn-cu12 ==8.9.2.26
Requires-Dist: nvidia-cufft-cu11 ==10.9.0.58
Requires-Dist: nvidia-cufft-cu12 ==11.0.2.54
Requires-Dist: nvidia-curand-cu11 ==10.2.10.91
Requires-Dist: nvidia-curand-cu12 ==10.3.2.106
Requires-Dist: nvidia-cusolver-cu11 ==11.4.0.1
Requires-Dist: nvidia-cusolver-cu12 ==11.4.5.107
Requires-Dist: nvidia-cusparse-cu11 ==11.7.4.91
Requires-Dist: nvidia-cusparse-cu12 ==12.1.0.106
Requires-Dist: nvidia-nccl-cu11 ==2.14.3
Requires-Dist: nvidia-nccl-cu12 ==2.20.5
Requires-Dist: nvidia-nvjitlink-cu12 ==12.4.127
Requires-Dist: nvidia-nvtx-cu11 ==11.7.91
Requires-Dist: nvidia-nvtx-cu12 ==12.1.105
Requires-Dist: packaging ==24.1
Requires-Dist: pandas ==2.0.3
Requires-Dist: peft ==0.3.0
Requires-Dist: pillow ==10.3.0
Requires-Dist: pkginfo ==1.10.0
Requires-Dist: pluggy ==1.5.0
Requires-Dist: POT ==0.9.4
Requires-Dist: preshed ==3.0.9
Requires-Dist: psutil ==5.9.8
Requires-Dist: pyarrow ==16.1.0
Requires-Dist: pyarrow-hotfix ==0.6
Requires-Dist: pybtex ==0.24.0
Requires-Dist: pybtex-docutils ==1.0.3
Requires-Dist: pycparser ==2.22
Requires-Dist: pydantic ==2.6.4
Requires-Dist: pydantic-core ==2.16.3
Requires-Dist: Pygments ==2.18.0
Requires-Dist: pyparsing ==3.1.2
Requires-Dist: pytest ==8.3.2
Requires-Dist: pytest-cov ==5.0.0
Requires-Dist: python-dateutil ==2.9.0.post0
Requires-Dist: pytorch-ignite ==0.5.0.post2
Requires-Dist: pytz ==2024.1
Requires-Dist: PyYAML ==6.0.1
Requires-Dist: readme-renderer ==43.0
Requires-Dist: recommonmark ==0.7.1
Requires-Dist: regex ==2023.12.25
Requires-Dist: requests ==2.32.3
Requires-Dist: requests-toolbelt ==1.0.0
Requires-Dist: rfc3986 ==2.0.0
Requires-Dist: rich ==13.7.1
Requires-Dist: safetensors ==0.4.2
Requires-Dist: scikit-learn ==1.3.2
Requires-Dist: scipy ==1.10.1
Requires-Dist: SecretStorage ==3.3.3
Requires-Dist: sentence-transformers ==3.0.1
Requires-Dist: six ==1.16.0
Requires-Dist: smart-open ==6.4.0
Requires-Dist: smmap ==5.0.1
Requires-Dist: sniffio ==1.3.1
Requires-Dist: snowballstemmer ==2.2.0
Requires-Dist: SocialED ==1.1.2
Requires-Dist: soupsieve ==2.5
Requires-Dist: spacy ==3.7.4
Requires-Dist: spacy-legacy ==3.0.12
Requires-Dist: spacy-loggers ==1.0.5
Requires-Dist: Sphinx ==7.1.2
Requires-Dist: sphinx-autodoc-typehints ==2.0.1
Requires-Dist: sphinx-basic-ng ==1.0.0b2
Requires-Dist: sphinx-gallery ==0.17.1
Requires-Dist: sphinx-rtd-theme ==2.0.0
Requires-Dist: sphinxcontrib-applehelp ==1.0.4
Requires-Dist: sphinxcontrib-bibtex ==2.6.2
Requires-Dist: sphinxcontrib-devhelp ==1.0.2
Requires-Dist: sphinxcontrib-htmlhelp ==2.0.1
Requires-Dist: sphinxcontrib-jquery ==4.1
Requires-Dist: sphinxcontrib-jsmath ==1.0.1
Requires-Dist: sphinxcontrib-qthelp ==1.0.3
Requires-Dist: sphinxcontrib-serializinghtml ==1.1.5
Requires-Dist: srsly ==2.4.8
Requires-Dist: starlette ==0.36.3
Requires-Dist: sympy ==1.12
Requires-Dist: thinc ==8.2.3
Requires-Dist: threadpoolctl ==3.5.0
Requires-Dist: tokenizers ==0.19.1
Requires-Dist: tomli ==2.0.1
Requires-Dist: torch ==2.3.1
Requires-Dist: torch-geometric ==2.6.1
Requires-Dist: tqdm ==4.66.4
Requires-Dist: transformers ==4.41.2
Requires-Dist: triton ==2.3.1
Requires-Dist: twine ==5.1.1
Requires-Dist: typer ==0.9.4
Requires-Dist: typing-extensions ==4.11.0
Requires-Dist: tzdata ==2024.1
Requires-Dist: urllib3 ==2.2.1
Requires-Dist: uvicorn ==0.29.0
Requires-Dist: wasabi ==1.1.2
Requires-Dist: weasel ==0.3.4
Requires-Dist: wrapt ==1.16.0
Requires-Dist: xxhash ==3.4.1
Requires-Dist: yarl ==1.9.4
Requires-Dist: zipp ==3.19.2
